README.md
setup.py
qualtrics_mailer/__init__.py
qualtrics_mailer/qualtrics_account.py
qualtrics_mailer/qualtrics_distribution.py
qualtrics_mailer/qualtrics_mailing_list.py
qualtrics_mailer.egg-info/PKG-INFO
qualtrics_mailer.egg-info/SOURCES.txt
qualtrics_mailer.egg-info/dependency_links.txt
qualtrics_mailer.egg-info/not-zip-safe
qualtrics_mailer.egg-info/requires.txt
qualtrics_mailer.egg-info/top_level.txt