Metadata-Version: 1.1
Name: qualtrics-mailer
Version: 0.1
Summary: A package for distributing pre-built surveys in Qualtrics
Home-page: http://github.com/kaianalytics/qualtrics_mailer
Author: Kai Analytics
Author-email: info@kaianalytics.com
License: MIT
Keywords: qualtrics survey
Platform: UNKNOWN
Classifier: Programming Language :: Python :: 3.6
